Workbook
Name NativeTimeline_Hiring_Date: #N/A
Name Slicer_Country: #N/A
Name Slicer_Department: #N/A
Name Slicer_Gender: #N/A
Name t: INDEX(([1]Lookup!XEX24:XEX1048570,[1]Lookup!XEW24:XEW1048570,[1]Lookup!XEY24:XEY1048570),,,2)

Sheet Sheet5
A1: ID | B1: First Name | C1: Last Name | D1: Full Name | E1: Gender | F1: Phone | G1: Country | H1: Work Type | I1: Department | J1: MonyTransfere | K1: Email | L1: Hire Day | M1: Hire Month | N1: Hire Year | O1: Hiring Date | P1: Experience Year | Q1: Salary | R1: Tax 10% | S1: Bonus 3% | T1: Net Salary | U1: Salary Status | V1: Extra Bonus
A2: 1001 | B2: Ghadir | C2: AhmeD | D2: Ghadir Ahmed | E2: Female | F2: 012-2910-2426 | G2: Sudan | H2: Full Time | I2: Manufacturing | J2: Debt Card | K2: g.ahmed@email.com | L2: 5 | M2: 4 | N2: 2023 | O2: 45021 | P2: 2 | Q2: 6548 | R2: 654.8 | S2: 196.44 | T2: 6089.64 | U2: over | V2: 0.02
A3: 1002 | B3: OmAr | C3: hisham | D3: Omar Hisham | E3: Male | F3: 011-2304-6179 | G3: Syria | H3: Contract | I3: Marketing | J3: Hawala | K3: o.hishan@email.com | L3: 6 | M3: 1 | N3: 2001 | O3: 36897 | P3: 25 | Q3: 7175 | R3: 717.5 | S3: 215.25 | T3: 6672.75 | U3: over | V3: 0.02
A4: 1003 | B4: Ailya | C4: ShaRaf | D4: Ailya Sharaf | E4: Female | F4: 012-4071-7821 | G4: Saudi Arabia | H4: Half-Time | I4: Manufacturing | J4: Debt Card | K4: a.sharaf@email.com | L4: 7 | M4: 1 | N4: 2007 | O4: 39089 | P4: 19 | Q4: 4070 | R4: 407 | S4: 122.1 | T4: 3785.1 | U4: normal | V4: 0.05
A5: 1004 | B5: Lwiy | C5: Qbany | D5: Lwiy Qbany | E5: Male | F5: 010-5618-2492 | G5: Sudan | H5: Full Time | I5: Account Management | J5: Hawala | K5: l.qbany@email.com | L5: 21 | M5: 1 | N5: 1993 | O5: 33990 | P5: 32 | Q5: 1906 | R5: 190.6 | S5: 57.18 | T5: 1772.58 | U5: normal | V5: 0.08
A6: 1005 | B6: Ahmad | C6: bikri | D6: Ahmad Bikri | E6: Male | F6: 011-7329-6122 | G6: Egypt | H6: Half-Time | I6: Account Management | J6: Hawala | K6: a.bikri@email.com | L6: 26 | M6: 1 | N6: 2019 | O6: 43491 | P6: 6 | Q6: 2600 | R6: 260 | S6: 78 | T6: 2418 | U6: normal | V6: 0.08
A7: 1006 | B7: Muhamad | C7: Zueitr | D7: Muhamad Zueitr | E7: Male | F7: 011-2527-4512 | G7: Saudi Arabia | H7: Contract | I7: Quality Control | J7: Hawala | K7: m.zueitr@email.com | L7: 26 | M7: 1 | N7: 2003 | O7: 37647 | P7: 22 | Q7: 3753 | R7: 375.3 | S7: 112.59 | T7: 3490.29 | U7: normal | V7: 0.05
A8: 1007 | B8: Iin | C8: Alhalaliu | D8: Iin Alhalaliu | E8: Female | F8: 012-2640-9521 | G8: Iraq | H8: Full Time | I8: Engineering | J8: Master Card | K8: i.alhalaliu@email.com | L8: 29 | M8: 1 | N8: 1994 | O8: 34363 | P8: 31 | Q8: 5086 | R8: 508.6 | S8: 152.58 | T8: 4729.98 | U8: normal | V8: 0.05
A9: 1008 | B9: Muhamad | C9: Alaya | D9: Muhamad Alaya | E9: Male | F9: 010-8241-1311 | G9: Saudi Arabia | H9: Hourly | I9: Manufacturing | J9: Western Union | K9: m.alaya@email.com | L9: 29 | M9: 1 | N9: 2012 | O9: 40937 | P9: 13 | Q9: 2431 | R9: 243.1 | S9: 72.93 | T9: 2260.83 | U9: normal | V9: 0.08
A10: 1009 | B10: Susin | C10: Almilat | D10: Susin Almilat | E10: Female | F10: 012-1039-8810 | G10: Egypt | H10: Full Time | I10: Manufacturing | J10: Hawala | K10: s.almilat@email.com | L10: 30 | M10: 1 | N10: 2004 | O10: 38016 | P10: 21 | Q10: 2955 | R10: 295.5 | S10: 88.65 | T10: 2748.15 | U10: normal | V10: 0.08
A11: 1010 | B11: Muhamad | C11: Alrifaei | D11: Muhamad Alrifaei | E11: Male | F11: 010-7467-7662 | G11: Egypt | H11: Half-Time | I11: Engineering | J11: Hawala | K11: m.alrifaei@email.com | L11: 11 | M11: 2 | N11: 2003 | O11: 37663 | P11: 22 | Q11: 1948 | R11: 194.8 | S11: 58.44 | T11: 1811.64 | U11: normal | V11: 0.08
A12: 1011 | B12: Muhamad | C12: Alqadah | D12: Muhamad Alqadah | E12: Male | F12: 011-8317-7634 | G12: Iraq | H12: Half-Time | I12: Marketing | J12: Western Union | K12: m.alqadah@email.com | L12: 11 | M12: 2 | N12: 1993 | O12: 34011 | P12: 32 | Q12: 3294 | R12: 329.4 | S12: 98.82 | T12: 3063.42 | U12: normal | V12: 0.05
A13: 1012 | B13: Muhamad | C13: Iad | D13: Muhamad Iad | E13: Male | F13: 011-6548-2919 | G13: Sudan | H13: Contract | I13: Engineering | J13: Debt Card | K13: m.iad@email.com | L13: 17 | M13: 2 | N13: 2005 | O13: 38400 | P13: 20 | Q13: 7123 | R13: 712.3 | S13: 213.69 | T13: 6624.39 | U13: over | V13: 0.02
... A301: 1300 | B301: Ahmad | C301: Qadimati | D301: Ahmad Qadimati | E301: Male | F301: 011-5056-6641 | G301: Iraq | H301: Full Time | I301: Marketing | J301: Western Union | K301: a.qadimati@email.com | L301: 8 | M301: 3 | N301: 2015 | O301: 42071 | P301: 10 | Q301: 3294 | R301: 329.4 | S301: 98.82 | T301: 3063.42 | U301: normal | V301: 0.05

Sheet Basic
A1: ID | B1: First Name | C1: Last Name | D1: Full Name | E1: Gender | F1: Phone | G1: Country | H1: Work Type | I1: Department | J1: MonyTransfere | K1: Email | L1: Hire Day | M1: Hire Month | N1: Hire Year | O1: Hiring Date | P1: Experience Year | Q1: Salary | R1: Tax 10% | S1: Bonus 3% | T1: Net Salary | U1: Salary Status | V1: Extra Bonus
A2: 1001 | B2: Ghadir | C2: AhmeD | D2: =PROPER(TRIM((B2 &" "& C2))) -> Ghadir Ahmed | E2: Female | F2: 012-2910-2426 | G2: Sudan | H2: Full Time | I2: Manufacturing | J2: Debt Card | K2: g.ahmed@email.com | L2: 5 | M2: 4 | N2: 2023 | O2: =DATE(N2,M2,L2) -> 45021 | P2: =DATEDIF(O2,TODAY(),"y") -> 3 | Q2: 6548 | R2: =Q2*0.1 -> 654.8 | S2: =Q2*0.03 -> 196.44 | T2: =Q2+S2-R2 -> 6089.64 | U2: =IF(T2>=6000,"over","normal") -> over | V2: =VLOOKUP(T2,$Y$6:$Z$10,2,TRUE) -> 0.02 | X2: Salary Status
A3: 1002 | B3: OmAr | C3: hisham | D3: =PROPER(TRIM((B3 &" "& C3))) -> Omar Hisham | E3: Male | F3: 011-2304-6179 | G3: Syria | H3: Contract | I3: Marketing | J3: Hawala | K3: o.hishan@email.com | L3: 6 | M3: 1 | N3: 2001 | O3: =DATE(N3,M3,L3) -> 36897 | P3: =DATEDIF(O3,TODAY(),"y") -> 25 | Q3: 7175 | R3: =Q3*0.1 -> 717.5 | S3: =Q3*0.03 -> 215.25 | T3: =Q3+S3-R3 -> 6672.75 | U3: =IF(T3>=6000,"over","normal") -> over | V3: =VLOOKUP(T3,$Y$6:$Z$10,2,TRUE) -> 0.02 | X3: = | Y3: Net >=6000 (Over) | Z3: Net <6000 (Normal)
A4: 1003 | B4: Ailya | C4: ShaRaf | D4: =PROPER(TRIM((B4 &" "& C4))) -> Ailya Sharaf | E4: Female | F4: 012-4071-7821 | G4: Saudi Arabia | H4: Half-Time | I4: Manufacturing | J4: Debt Card | K4: a.sharaf@email.com | L4: 7 | M4: 1 | N4: 2007 | O4: =DATE(N4,M4,L4) -> 39089 | P4: =DATEDIF(O4,TODAY(),"y") -> 19 | Q4: 4070 | R4: =Q4*0.1 -> 407 | S4: =Q4*0.03 -> 122.1 | T4: =Q4+S4-R4 -> 3785.1 | U4: =IF(T4>=6000,"over","normal") -> normal | V4: =VLOOKUP(T4,$Y$6:$Z$10,2,TRUE) -> 0.05
A5: 1004 | B5: Lwiy | C5: Qbany | D5: =PROPER(TRIM((B5 &" "& C5))) -> Lwiy Qbany | E5: Male | F5: 010-5618-2492 | G5: Sudan | H5: Full Time | I5: Account Management | J5: Hawala | K5: l.qbany@email.com | L5: 21 | M5: 1 | N5: 1993 | O5: =DATE(N5,M5,L5) -> 33990 | P5: =DATEDIF(O5,TODAY(),"y") -> 33 | Q5: 1906 | R5: =Q5*0.1 -> 190.6 | S5: =Q5*0.03 -> 57.18 | T5: =Q5+S5-R5 -> 1772.58 | U5: =IF(T5>=6000,"over","normal") -> normal | V5: =VLOOKUP(T5,$Y$6:$Z$10,2,TRUE) -> 0.08 | Y5: Extra Bonus
A6: 1005 | B6: Ahmad | C6: bikri | D6: =PROPER(TRIM((B6 &" "& C6))) -> Ahmad Bikri | E6: Male | F6: 011-7329-6122 | G6: Egypt | H6: Half-Time | I6: Account Management | J6: Hawala | K6: a.bikri@email.com | L6: 26 | M6: 1 | N6: 2019 | O6: =DATE(N6,M6,L6) -> 43491 | P6: =DATEDIF(O6,TODAY(),"y") -> 7 | Q6: 2600 | R6: =Q6*0.1 -> 260 | S6: =Q6*0.03 -> 78 | T6: =Q6+S6-R6 -> 2418 | U6: =IF(T6>=6000,"over","normal") -> normal | V6: =VLOOKUP(T6,$Y$6:$Z$10,2,TRUE) -> 0.08 | Y6: Net Salary | Z6: Extra Bonus %
A7: 1006 | B7: Muhamad | C7: Zueitr | D7: =PROPER(TRIM((B7 &" "& C7))) -> Muhamad Zueitr | E7: Male | F7: 011-2527-4512 | G7: Saudi Arabia | H7: Contract | I7: Quality Control | J7: Hawala | K7: m.zueitr@email.com | L7: 26 | M7: 1 | N7: 2003 | O7: =DATE(N7,M7,L7) -> 37647 | P7: =DATEDIF(O7,TODAY(),"y") -> 23 | Q7: 3753 | R7: =Q7*0.1 -> 375.3 | S7: =Q7*0.03 -> 112.59 | T7: =Q7+S7-R7 -> 3490.29 | U7: =IF(T7>=6000,"over","normal") -> normal | V7: =VLOOKUP(T7,$Y$6:$Z$10,2,TRUE) -> 0.05 | Y7: 1 | Z7: 0.1
A8: 1007 | B8: Iin | C8: Alhalaliu | D8: =PROPER(TRIM((B8 &" "& C8))) -> Iin Alhalaliu | E8: Female | F8: 012-2640-9521 | G8: Iraq | H8: Full Time | I8: Engineering | J8: Master Card | K8: i.alhalaliu@email.com | L8: 29 | M8: 1 | N8: 1994 | O8: =DATE(N8,M8,L8) -> 34363 | P8: =DATEDIF(O8,TODAY(),"y") -> 32 | Q8: 5086 | R8: =Q8*0.1 -> 508.6 | S8: =Q8*0.03 -> 152.58 | T8: =Q8+S8-R8 -> 4729.98 | U8: =IF(T8>=6000,"over","normal") -> normal | V8: =VLOOKUP(T8,$Y$6:$Z$10,2,TRUE) -> 0.05 | Y8: 1000 | Z8: 0.08
A9: 1008 | B9: Muhamad | C9: Alaya | D9: =PROPER(TRIM((B9 &" "& C9))) -> Muhamad Alaya | E9: Male | F9: 010-8241-1311 | G9: Saudi Arabia | H9: Hourly | I9: Manufacturing | J9: Western Union | K9: m.alaya@email.com | L9: 29 | M9: 1 | N9: 2012 | O9: =DATE(N9,M9,L9) -> 40937 | P9: =DATEDIF(O9,TODAY(),"y") -> 14 | Q9: 2431 | R9: =Q9*0.1 -> 243.1 | S9: =Q9*0.03 -> 72.93 | T9: =Q9+S9-R9 -> 2260.83 | U9: =IF(T9>=6000,"over","normal") -> normal | V9: =VLOOKUP(T9,$Y$6:$Z$10,2,TRUE) -> 0.08 | Y9: 3000 | Z9: 0.05
A10: 1009 | B10: Susin | C10: Almilat | D10: =PROPER(TRIM((B10 &" "& C10))) -> Susin Almilat | E10: Female | F10: 012-1039-8810 | G10: Egypt | H10: Full Time | I10: Manufacturing | J10: Hawala | K10: s.almilat@email.com | L10: 30 | M10: 1 | N10: 2004 | O10: =DATE(N10,M10,L10) -> 38016 | P10: =DATEDIF(O10,TODAY(),"y") -> 22 | Q10: 2955 | R10: =Q10*0.1 -> 295.5 | S10: =Q10*0.03 -> 88.65 | T10: =Q10+S10-R10 -> 2748.15 | U10: =IF(T10>=6000,"over","normal") -> normal | V10: =VLOOKUP(T10,$Y$6:$Z$10,2,TRUE) -> 0.08 | Y10: 6000 | Z10: 0.02
A11: 1010 | B11: Muhamad | C11: Alrifaei | D11: =PROPER(TRIM((B11 &" "& C11))) -> Muhamad Alrifaei | E11: Male | F11: 010-7467-7662 | G11: Egypt | H11: Half-Time | I11: Engineering | J11: Hawala | K11: m.alrifaei@email.com | L11: 11 | M11: 2 | N11: 2003 | O11: =DATE(N11,M11,L11) -> 37663 | P11: =DATEDIF(O11,TODAY(),"y") -> 23 | Q11: 1948 | R11: =Q11*0.1 -> 194.8 | S11: =Q11*0.03 -> 58.44 | T11: =Q11+S11-R11 -> 1811.64 | U11: =IF(T11>=6000,"over","normal") -> normal | V11: =VLOOKUP(T11,$Y$6:$Z$10,2,TRUE) -> 0.08
A12: 1011 | B12: Muhamad | C12: Alqadah | D12: =PROPER(TRIM((B12 &" "& C12))) -> Muhamad Alqadah | E12: Male | F12: 011-8317-7634 | G12: Iraq | H12: Half-Time | I12: Marketing | J12: Western Union | K12: m.alqadah@email.com | L12: 11 | M12: 2 | N12: 1993 | O12: =DATE(N12,M12,L12) -> 34011 | P12: =DATEDIF(O12,TODAY(),"y") -> 33 | Q12: 3294 | R12: =Q12*0.1 -> 329.4 | S12: =Q12*0.03 -> 98.82 | T12: =Q12+S12-R12 -> 3063.42 | U12: =IF(T12>=6000,"over","normal") -> normal | V12: =VLOOKUP(T12,$Y$6:$Z$10,2,TRUE) -> 0.05
A13: 1012 | B13: Muhamad | C13: Iad | D13: =PROPER(TRIM((B13 &" "& C13))) -> Muhamad Iad | E13: Male | F13: 011-6548-2919 | G13: Sudan | H13: Contract | I13: Engineering | J13: Debt Card | K13: m.iad@email.com | L13: 17 | M13: 2 | N13: 2005 | O13: =DATE(N13,M13,L13) -> 38400 | P13: =DATEDIF(O13,TODAY(),"y") -> 21 | Q13: 7123 | R13: =Q13*0.1 -> 712.3 | S13: =Q13*0.03 -> 213.69 | T13: =Q13+S13-R13 -> 6624.39 | U13: =IF(T13>=6000,"over","normal") -> over | V13: =VLOOKUP(T13,$Y$6:$Z$10,2,TRUE) -> 0.02
A14: 1013 | B14: Razaan | C14: Nasif | D14: =PROPER(TRIM((B14 &" "& C14))) -> Razaan Nasif | E14: Female | F14: 010-6241-6559 | G14: Saudi Arabia | H14: Full Time | I14: Marketing | J14: Debt Card | K14: r.nasif@email.com | L14: 25 | M14: 2 | N14: 2019 | O14: =DATE(N14,M14,L14) -> 43521 | P14: =DATEDIF(O14,TODAY(),"y") -> 7 | Q14: 7236 | R14: =Q14*0.1 -> 723.6 | S14: =Q14*0.03 -> 217.08 | T14: =Q14+S14-R14 -> 6729.48 | U14: =IF(T14>=6000,"over","normal") -> over | V14: =VLOOKUP(T14,$Y$6:$Z$10,2,TRUE) -> 0.02
A15: 1014 | B15: Iilian | C15: mohamed | D15: =PROPER(TRIM((B15 &" "& C15))) -> Iilian Mohamed | E15: Female | F15: 012-0080-0351 | G15: Sudan | H15: Full Time | I15: Engineering | J15: Hawala | K15: i.dbs@email.com | L15: 26 | M15: 2 | N15: 2004 | O15: =DATE(N15,M15,L15) -> 38043 | P15: =DATEDIF(O15,TODAY(),"y") -> 22 | Q15: 6843 | R15: =Q15*0.1 -> 684.3 | S15: =Q15*0.03 -> 205.29 | T15: =Q15+S15-R15 -> 6363.99 | U15: =IF(T15>=6000,"over","normal") -> over | V15: =VLOOKUP(T15,$Y$6:$Z$10,2,TRUE) -> 0.02
A16: 1015 | B16: Bayan | C16: mostafa | D16: =PROPER(TRIM((B16 &" "& C16))) -> Bayan Mostafa | E16: Female | F16: 011-5953-5296 | G16: Sudan | H16: Hourly | I16: Engineering | J16: Hawala | K16: b.qdw@email.com | L16: 2 | M16: 3 | N16: 2011 | O16: =DATE(N16,M16,L16) -> 40604 | P16: =DATEDIF(O16,TODAY(),"y") -> 15 | Q16: 1070 | R16: =Q16*0.1 -> 107 | S16: =Q16*0.03 -> 32.1 | T16: =Q16+S16-R16 -> 995.1 | U16: =IF(T16>=6000,"over","normal") -> normal | V16: =VLOOKUP(T16,$Y$6:$Z$10,2,TRUE) -> 0.1
A17: 1016 | B17: Alaa | C17: Muhamad | D17: =PROPER(TRIM((B17 &" "& C17))) -> Alaa Muhamad | E17: Male | F17: 010-5319-7669 | G17: Saudi Arabia | H17: Hourly | I17: Engineering | J17: Debt Card | K17: a.muhamad@email.com | L17: 10 | M17: 3 | N17: 2020 | O17: =DATE(N17,M17,L17) -> 43900 | P17: =DATEDIF(O17,TODAY(),"y") -> 6 | Q17: 1493 | R17: =Q17*0.1 -> 149.3 | S17: =Q17*0.03 -> 44.79 | T17: =Q17+S17-R17 -> 1388.49 | U17: =IF(T17>=6000,"over","normal") -> normal | V17: =VLOOKUP(T17,$Y$6:$Z$10,2,TRUE) -> 0.08
A18: 1017 | B18: Sandra | C18: Ziad | D18: =PROPER(TRIM((B18 &" "& C18))) -> Sandra Ziad | E18: Female | F18: 011-2332-0982 | G18: Iraq | H18: Full Time | I18: Marketing | J18: Hawala | K18: s.ziad@email.com | L18: 6 | M18: 4 | N18: 1999 | O18: =DATE(N18,M18,L18) -> 36256 | P18: =DATEDIF(O18,TODAY(),"y") -> 27 | Q18: 5857 | R18: =Q18*0.1 -> 585.7 | S18: =Q18*0.03 -> 175.71 | T18: =Q18+S18-R18 -> 5447.01 | U18: =IF(T18>=6000,"over","normal") -> normal | V18: =VLOOKUP(T18,$Y$6:$Z$10,2,TRUE) -> 0.05
A19: 1018 | B19: Farahad | C19: Husayn | D19: =PROPER(TRIM((B19 &" "& C19))) -> Farahad Husayn | E19: Male | F19: 010-1442-5932 | G19: Iraq | H19: Contract | I19: IT | J19: Hawala | K19: f.husayn@email.com | L19: 12 | M19: 4 | N19: 2004 | O19: =DATE(N19,M19,L19) -> 38089 | P19: =DATEDIF(O19,TODAY(),"y") -> 22 | Q19: 5278 | R19: =Q19*0.1 -> 527.8 | S19: =Q19*0.03 -> 158.34 | T19: =Q19+S19-R19 -> 4908.54 | U19: =IF(T19>=6000,"over","normal") -> normal | V19: =VLOOKUP(T19,$Y$6:$Z$10,2,TRUE) -> 0.05
A20: 1019 | B20: Ahed | C20: Salim | D20: =PROPER(TRIM((B20 &" "& C20))) -> Ahed Salim | E20: Female | F20: 011-6732-2351 | G20: Sudan | H20: Full Time | I20: IT | J20: Hawala | K20: a.salim@email.com | L20: 13 | M20: 4 | N20: 1999 | O20: =DATE(N20,M20,L20) -> 36263 | P20: =DATEDIF(O20,TODAY(),"y") -> 27 | Q20: 5710 | R20: =Q20*0.1 -> 571 | S20: =Q20*0.03 -> 171.3 | T20: =Q20+S20-R20 -> 5310.3 | U20: =IF(T20>=6000,"over","normal") -> normal | V20: =VLOOKUP(T20,$Y$6:$Z$10,2,TRUE) -> 0.05
A21: 1020 | B21: Ayham | C21: Tutwnji | D21: =PROPER(TRIM((B21 &" "& C21))) -> Ayham Tutwnji | E21: Male | F21: 011-8295-8045 | G21: Saudi Arabia | H21: Full Time | I21: Account Management | J21: Hawala | K21: a.tutwnji@email.com | L21: 28 | M21: 4 | N21: 2020 | O21: =DATE(N21,M21,L21) -> 43949 | P21: =DATEDIF(O21,TODAY(),"y") -> 5 | Q21: 6145 | R21: =Q21*0.1 -> 614.5 | S21: =Q21*0.03 -> 184.35 | T21: =Q21+S21-R21 -> 5714.85 | U21: =IF(T21>=6000,"over","normal") -> normal | V21: =VLOOKUP(T21,$Y$6:$Z$10,2,TRUE) -> 0.05
A22: 1021 | B22: Samir | C22: Alsafdi | D22: =PROPER(TRIM((B22 &" "& C22))) -> Samir Alsafdi | E22: Male | F22: 010-8655-8298 | G22: Egypt | H22: Contract | I22: IT | J22: Western Union | K22: s.alsafdi@email.com | L22: 1 | M22: 5 | N22: 2012 | O22: =DATE(N22,M22,L22) -> 41030 | P22: =DATEDIF(O22,TODAY(),"y") -> 13 | Q22: 5278 | R22: =Q22*0.1 -> 527.8 | S22: =Q22*0.03 -> 158.34 | T22: =Q22+S22-R22 -> 4908.54 | U22: =IF(T22>=6000,"over","normal") -> normal | V22: =VLOOKUP(T22,$Y$6:$Z$10,2,TRUE) -> 0.05
... A301: 1300 | B301: Ahmad | C301: Qadimati | D301: =PROPER(TRIM((B301 &" "& C301))) -> Ahmad Qadimati | E301: Male | F301: 011-5056-6641 | G301: Iraq | H301: Full Time | I301: Marketing | J301: Western Union | K301: a.qadimati@email.com | L301: 8 | M301: 3 | N301: 2015 | O301: =DATE(N301,M301,L301) -> 42071 | P301: =DATEDIF(O301,TODAY(),"y") -> 11 | Q301: 3294 | R301: =Q301*0.1 -> 329.4 | S301: =Q301*0.03 -> 98.82 | T301: =Q301+S301-R301 -> 3063.42 | U301: =IF(T301>=6000,"over","normal") -> normal | V301: =VLOOKUP(T301,$Y$6:$Z$10,2,TRUE) -> 0.05

Sheet Dashboard Required
A1: Dashboard Required
A2: 1 | B2: Count of Employees
A3: 2 | B3: Total Salaries
A4: 3 | B4: AVG. of Experience Year
A5: 4 | B5: Count of Employees by Gender
A6: 5 | B6: Count of Employees by MonyTransfere
A7: 6 | B7: Count of Employees by Countries
A8: 7 | B8: Count of Employees by Extra Bonus
A9: 8 | B9: Count of Employees by Department and Work Types | E9: Country | F9: Count of Full Name
A10: 9 | B10: Total Salaries and Count of Employees by Hiring Year | E10: Egypt | F10: 99
A11: 10 | B11: add the Following Slicers: | E11: Iraq | F11: 53
B12: Gender - Country - Department - Hiring Date (time line ) | E12: Saudi Arabia | F12: 72
E13: Sudan | F13: 61
E14: Syria | F14: 15

Sheet Sheet1
A1: =Sheet3!L3 -> Country | B1: =Sheet3!M3 -> Count of Full Name
A2: =Sheet3!L4 -> Egypt | B2: =Sheet3!M4 -> 99
A3: =Sheet3!L5 -> Iraq | B3: =Sheet3!M5 -> 53
A4: =Sheet3!L6 -> Saudi Arabia | B4: =Sheet3!M6 -> 72
A5: =Sheet3!L7 -> Sudan | B5: =Sheet3!M7 -> 61
A6: =Sheet3!L8 -> Syria | B6: =Sheet3!M8 -> 15
B11: =Sheet3!$AD$13 -> 300 | C11: =Sheet3!$AD$13 -> 300 | E11: =Sheet3!$AF$13 -> 1336352
D18: =Sheet3!$F$4 -> 19.116667

Sheet Sheet3
A3: Count of Full Name | C3: Gender | D3: Count of employes by gender | F3: Average of Experience Year | I3: MonyTransfere | J3: c O g | L3: Country | M3: Count of Full Name | O3: Extra Bonus | P3: cOf | R3: Department | S3: Count of Work Type | U3: Hiring Date | V3: sos | W3: cfn | Z3: Country | AA3: Count of Full Name
A4: 300 | C4: Female | D4: 115 | F4: 19.116667 | I4: Debt Card | J4: 111 | L4: Egypt | M4: 99 | O4: 0.02 | P4: 52 | R4: Account Management | S4: 39 | U4: Jan | V4: 132228 | W4: 31 | Z4: Egypt | AA4: 99
C5: Male | D5: 185 | I5: Hawala | J5: 92 | L5: Iraq | M5: 53 | O5: 0.05 | P5: 150 | R5: Creative | S5: 5 | U5: Feb | V5: 138136 | W5: 28 | Z5: Iraq | AA5: 53
I6: Master Card | J6: 44 | L6: Saudi Arabia | M6: 72 | O6: 0.08 | P6: 84 | R6: Engineering | S6: 55 | U6: Mar | V6: 68448 | W6: 22 | Z6: Saudi Arabia | AA6: 72
I7: Western Union | J7: 53 | L7: Sudan | M7: 61 | O7: 0.1 | P7: 14 | R7: IT | S7: 24 | U7: Apr | V7: 118123 | W7: 26 | Z7: Sudan | AA7: 61
L8: Syria | M8: 15 | R8: Manufacturing | S8: 71 | U8: May | V8: 131899 | W8: 25 | Z8: Syria | AA8: 15
R9: Marketing | S9: 65 | U9: Jun | V9: 102806 | W9: 23
R10: Product Development | S10: 10 | U10: Jul | V10: 131906 | W10: 29
R11: Quality Control | S11: 15 | U11: Aug | V11: 81090 | W11: 19
R12: Sales | S12: 16 | U12: Sep | V12: 148445 | W12: 32 | AD12: Count of Full Name | AF12: Sum of Salary
U13: Oct | V13: 90857 | W13: 24 | AD13: 300 | AF13: 1336352
U14: Nov | V14: 85387 | W14: 20
U15: Dec | V15: 107027 | W15: 21
L99: =L3 -> Country | M99: =M3 -> Count of Full Name
L100: =L4 -> Egypt | M100: =M4 -> 99
L101: =L5 -> Iraq | M101: =M5 -> 53
L102: =L6 -> Saudi Arabia | M102: =M6 -> 72
L103: =L7 -> Sudan | M103: =M7 -> 61
L104: =L8 -> Syria | M104: =M8 -> 15

Sheet Sheet6

Sheet MAIN DASH

Sheet SEC DASH
